Workbook

Sheet Lisez-moi
A1: Rentabilité DineroX par formule et par territoire
A3: Comment s'en servir
A4: 1. Changez seulement les cellules en bleu sur fond jaune, dans l'onglet « Hypothèses ».
A5: 2. Les onglets « Afrique », « Europe » et « Seuil Pro » se recalculent tout seuls.
A6: 3. Textes en noir = calculs (ne pas modifier). Textes en vert = valeur reprise d'un autre onglet.
A8: Ce que le tableur calcule
A9: Pour chaque formule : ce que paient les clients, moins la TVA, moins la commission Google (15 %),
A10: moins les frais de paiement, moins les coûts techniques par personne active = la marge de DineroX.
A11: La formule Pro est facturée directement à l'entreprise : ni commission Google, ni TVA prise sur le prix
A12: (la TVA s'ajoute à la facture et l'entreprise la récupère).
A14: Ce que le tableur ne compte pas
A15: Les coûts fixes : salaires, publicité, socle Firebase, domaine, comptable. Les marges servent à les payer.
... A23: Pro 2 000 F / 7,99 € par employé et par mois, à partir de 5 employés (minimum facturé : 5 places).

Sheet Hypothèses
A1: Hypothèses (cellules bleues sur fond jaune : à modifier)
A3: Général
A4: Taux de change : 1 € en F CFA | B4: 655.957
A5: Commission Google Play sur un abonnement | B5: 0.15
A7: Afrique
A8: Prix Plus (F CFA / mois) | B8: 2000
A9: Prix Famille (F CFA / mois) | B9: 3500
A10: Prix Pro (F CFA / employé / mois, hors TVA) | B10: 2000
A11: TVA incluse dans le prix Google Play | B11: 0.18
A12: Frais de paiement Pro (Mobile Money, virement) | B12: 0.015
A13: Coût de gestion par entreprise Pro (F CFA / mois) | B13: 2000
A14: Coût Firebase par personne active (F CFA / mois) | B14: 30
A15: Coût intelligence artificielle par personne active (F CFA / mois) | B15: 60
A16: Coût voix ElevenLabs par personne active (F CFA / mois) | B16: 400
A18: Europe
A19: Prix Plus (€ / mois) | B19: 9.99
A20: Prix Famille (€ / mois) | B20: 14.99
A21: Prix Pro (€ / employé / mois, hors TVA) | B21: 7.99
A22: TVA incluse dans le prix Google Play | B22: 0.2
A23: Frais de paiement Pro (virement, prélèvement) | B23: 0.005
A24: Coût de gestion par entreprise Pro (€ / mois) | B24: 3
A25: Coûts techniques par personne active (€ / mois) | B25: =(B14+B15+B16)/B4
A27: Utilisateurs
A28: Personnes actives Plus | B28: 1000
A29: Personnes actives Famille | B29: 1000
A30: Personnes actives par abonnement Famille | B30: 3
A32: Formule Pro : entreprises clientes (même répartition en Afrique et en Europe)
A33: Seuil : employés minimum pour la formule Pro | B33: 5
A34: Taille de l'entreprise (employés) | B34: Nombre d'entreprises | C34: Employés
A35: 5 | B35: 40 | C35: =A35*B35
A36: 10 | B36: 40 | C36: =A36*B36
A37: 20 | B37: 20 | C37: =A37*B37
A38: Total | B38: =SUM(B35:B37) | C38: =SUM(C35:C37)
A39: Contrôle du seuil | B39: =IF(MIN(A35:A37)>=B33,"OK : toutes les tailles respectent le seuil","Attention : une taille est sous le seuil")

Sheet Afrique
A1: Afrique : marge pour DineroX, par mois (montants en F CFA)
B3: Plus | C3: Famille | D3: Pro
A4: Personnes actives | B4: =Hypothèses!$B$28 | C4: =Hypothèses!$B$29 | D4: =Hypothèses!$C$38
A5: Abonnements (Pro : places payées) | B5: =B4 | C5: =ROUNDUP(C4/Hypothèses!$B$30,0) | D5: =D4
A6: Entreprises clientes (Pro) | B6: 0 | C6: 0 | D6: =Hypothèses!$B$38
A7: Prix par abonnement ou par place | B7: =Hypothèses!$B$8 | C7: =Hypothèses!$B$9 | D7: =Hypothèses!$B$10
A8: Encaissé auprès des clients | B8: =B5*B7 | C8: =C5*C7 | D8: =D5*D7
A9: − TVA comprise dans le prix | B9: =B8-B8/(1+Hypothèses!$B$11) | C9: =C8-C8/(1+Hypothèses!$B$11) | D9: 0
A10: − Commission Google (15 %) | B10: =(B8-B9)*Hypothèses!$B$5 | C10: =(C8-C9)*Hypothèses!$B$5 | D10: 0
A11: − Frais de paiement | B11: 0 | C11: 0 | D11: =D8*Hypothèses!$B$12
A12: =Reçu par DineroX | B12: =B8-B9-B10-B11 | C12: =C8-C9-C10-C11 | D12: =D8-D9-D10-D11
A13: − Coûts techniques (personnes actives) | B13: =B4*(Hypothèses!$B$14+Hypothèses!$B$15+Hypothèses!$B$16) | C13: =C4*(Hypothèses!$B$14+Hypothèses!$B$15+Hypothèses!$B$16) | D13: =D4*(Hypothèses!$B$14+Hypothèses!$B$15+Hypothèses!$B$16)
A14: − Coût de gestion des entreprises (Pro) | B14: 0 | C14: 0 | D14: =D6*Hypothèses!$B$13
A15: =Marge par mois | B15: =B12-B13-B14 | C15: =C12-C13-C14 | D15: =D12-D13-D14
A16: Marge par abonnement ou par place | B16: =IF(B5=0,0,B15/B5) | C16: =IF(C5=0,0,C15/C5) | D16: =IF(D5=0,0,D15/D5)
A17: Marge par personne active | B17: =IF(B4=0,0,B15/B4) | C17: =IF(C4=0,0,C15/C4) | D17: =IF(D4=0,0,D15/D4)
A18: Part de l'encaissé qui reste en marge | B18: =IF(B8=0,0,B15/B8) | C18: =IF(C8=0,0,C15/C8) | D18: =IF(D8=0,0,D15/D8)
A19: =Marge sur un an | B19: =B15*12 | C19: =C15*12 | D19: =D15*12
A21: Notes
A22: Famille : abonnements = personnes actives ÷ membres actifs par famille, arrondi au-dessus.
A23: Pro : facturé à l'entreprise hors TVA (la TVA s'ajoute à la facture) ; pas de commission Google.
A24: Coûts fixes (salaires, publicité, socle Firebase…) non compris.

Sheet Europe
A1: Europe : marge pour DineroX, par mois (montants en euros)
B3: Plus | C3: Famille | D3: Pro
A4: Personnes actives | B4: =Hypothèses!$B$28 | C4: =Hypothèses!$B$29 | D4: =Hypothèses!$C$38
A5: Abonnements (Pro : places payées) | B5: =B4 | C5: =ROUNDUP(C4/Hypothèses!$B$30,0) | D5: =D4
A6: Entreprises clientes (Pro) | B6: 0 | C6: 0 | D6: =Hypothèses!$B$38
A7: Prix par abonnement ou par place | B7: =Hypothèses!$B$19 | C7: =Hypothèses!$B$20 | D7: =Hypothèses!$B$21
A8: Encaissé auprès des clients | B8: =B5*B7 | C8: =C5*C7 | D8: =D5*D7
A9: − TVA comprise dans le prix | B9: =B8-B8/(1+Hypothèses!$B$22) | C9: =C8-C8/(1+Hypothèses!$B$22) | D9: 0
A10: − Commission Google (15 %) | B10: =(B8-B9)*Hypothèses!$B$5 | C10: =(C8-C9)*Hypothèses!$B$5 | D10: 0
A11: − Frais de paiement | B11: 0 | C11: 0 | D11: =D8*Hypothèses!$B$23
A12: =Reçu par DineroX | B12: =B8-B9-B10-B11 | C12: =C8-C9-C10-C11 | D12: =D8-D9-D10-D11
A13: − Coûts techniques (personnes actives) | B13: =B4*Hypothèses!$B$25 | C13: =C4*Hypothèses!$B$25 | D13: =D4*Hypothèses!$B$25
A14: − Coût de gestion des entreprises (Pro) | B14: 0 | C14: 0 | D14: =D6*Hypothèses!$B$24
A15: =Marge par mois | B15: =B12-B13-B14 | C15: =C12-C13-C14 | D15: =D12-D13-D14
A16: Marge par abonnement ou par place | B16: =IF(B5=0,0,B15/B5) | C16: =IF(C5=0,0,C15/C5) | D16: =IF(D5=0,0,D15/D5)
A17: Marge par personne active | B17: =IF(B4=0,0,B15/B4) | C17: =IF(C4=0,0,C15/C4) | D17: =IF(D4=0,0,D15/D4)
A18: Part de l'encaissé qui reste en marge | B18: =IF(B8=0,0,B15/B8) | C18: =IF(C8=0,0,C15/C8) | D18: =IF(D8=0,0,D15/D8)
A19: =Marge sur un an | B19: =B15*12 | C19: =C15*12 | D19: =D15*12
A21: Notes
A22: Famille : abonnements = personnes actives ÷ membres actifs par famille, arrondi au-dessus.
A23: Pro : facturé à l'entreprise hors TVA (la TVA s'ajoute à la facture) ; pas de commission Google.
A24: Coûts fixes (salaires, publicité, socle Firebase…) non compris.

Sheet Seuil Pro
A1: Formule Pro en Afrique : seuil de 5 ou de 10 employés (pour 1 000 employés)
A2: Même gain par place ; seul change le coût de gestion, qui dépend du nombre d'entreprises.
B4: Seuil à 10 | C4: Seuil à 5
A5: Entreprises clientes (exemple de répartition) | B5: 60 | C5: =Hypothèses!B38
A6: Employés | B6: 1000 | C6: =Hypothèses!C38
A7: Reçu par DineroX (après frais de paiement) | B7: =B6*Hypothèses!$B$10*(1-Hypothèses!$B$12) | C7: =C6*Hypothèses!$B$10*(1-Hypothèses!$B$12)
A8: − Coûts techniques | B8: =B6*(Hypothèses!$B$14+Hypothèses!$B$15+Hypothèses!$B$16) | C8: =C6*(Hypothèses!$B$14+Hypothèses!$B$15+Hypothèses!$B$16)
A9: − Coût de gestion des entreprises | B9: =B5*Hypothèses!$B$13 | C9: =C5*Hypothèses!$B$13
A10: =Marge par mois | B10: =B7-B8-B9 | C10: =C7-C8-C9
A11: Écart de marge du seuil à 5 par rapport au seuil à 10 | C11: =IF(B10=0,0,C10/B10-1)
A13: Lecture : le seuil à 5 coûte quelques pour cent de marge, mais ouvre la formule aux très nombreuses petites entreprises africaines.
